oestatpy/__init__.py
oestatpy/logic.py
oestatpy/table.py
oestatpy/tools.py
oestatpy-0.0.4.dist-info/METADATA
oestatpy-0.0.4.dist-info/WHEEL
oestatpy-0.0.4.dist-info/top_level.txt
oestatpy-0.0.4.dist-info/RECORD
