Metadata-Version: 2.1
Name: oestatpy
Version: 0.0.4
Requires-Dist: numpy
